{
    "forge_marker": 1,
    "defaults": {
        "model": "atlascore:tool"
    },
    "variants": {
		"sword": [{ "textures": { "layer0": "kinematica:items/tools/copper_sword" }}],
		"spade": [{ "textures": { "layer0": "kinematica:items/tools/copper_shovel" }}],
		"pickaxe": [{ "textures": { "layer0": "kinematica:items/tools/copper_pickaxe" }}],
		"axe": [{ "textures": { "layer0": "kinematica:items/tools/copper_axe" }}],
		"hoe": [{ "textures": { "layer0": "kinematica:items/tools/copper_hoe" }}]
    }
}
